cv_basic_utils/__init__.py
cv_basic_utils/path_utils/__init__.py
cv_basic_utils/path_utils/path_utils.py
cv_basic_utils/subpackage1/__init__.py
cv_basic_utils/subpackage1/moduleA.py
cv_basic_utils/subpackage2/__init__.py
cv_basic_utils/subpackage2/moduleB.py
cv_basic_utils-0.0.4.dist-info/LICENSE
cv_basic_utils-0.0.4.dist-info/METADATA
cv_basic_utils-0.0.4.dist-info/WHEEL
cv_basic_utils-0.0.4.dist-info/top_level.txt
cv_basic_utils-0.0.4.dist-info/RECORD
