Metadata-Version: 2.1
Name: cv-basic-utils
Version: 0.0.4
Summary: Common utils for machine learning, computer vision
Home-page: https://github.com/jerinka/cv_basic_utils
Author: Jerin K A
Author-email: jerin.electronics@gmail.com
License: UNKNOWN
Download-URL: https://github.com/jerinka/cv_basic_utils/archive/refs/tags/v0.0.3.tar.gz
Keywords: machine-learning,utils,vision-utils
Platform: UNKNOWN
License-File: LICENSE
Requires-Dist: pytest
Requires-Dist: coverage
